metaport/__init__.py
metaport/__main__.py
metaport/cli.py
metaport/config_manager.py
metaport/dependency_scanner.py
metaport/email_transport.py
metaport/encryption_manager.py
metaport/https_transport.py
metaport/installed_packages.py
metaport/metaport.py
metaport/models.py
metaport/pipenv_parser.py
metaport/poetry_parser.py
metaport/requirements_parser.py
metaport/sbom_generator.py
metaport/ssl_utils.py
metaport/vulnerability_scanner.py
metaport_agent_python-1.0.19.dist-info/licenses/LICENSE.txt
metaport_agent_python-1.0.19.dist-info/METADATA
metaport_agent_python-1.0.19.dist-info/WHEEL
metaport_agent_python-1.0.19.dist-info/entry_points.txt
metaport_agent_python-1.0.19.dist-info/top_level.txt
metaport_agent_python-1.0.19.dist-info/RECORD
