Metadata-Version: 2.4
Name: metaport-agent-python
Version: 1.0.19
Summary: Python agent for Metaport SBOM generation and reporting
Author-email: Dcentrica Solutions <hello@dcentrica.com>
License: BSD-3
Project-URL: Homepage, https://getmetaport.com
Project-URL: Documentation, https://docs.metaport.sh
Project-URL: Repository, https://gitlab.com/dcentrica/metaport/metaport-agent-python
Project-URL: Issues, https://gitlab.com/dcentrica/metaport/metaport-agent-python/-/issues
Keywords: metaport,sbom,security,dependencies,vulnerability,scanning
Classifier: Development Status :: 4 - Beta
Classifier: Intended Audience :: Developers
Classifier: Intended Audience :: System Administrators
Classifier: License :: OSI Approved :: MIT License
Classifier: Operating System :: OS Independent
Classifier: Programming Language :: Python
Classifier: Programming Language :: Python :: 3
Classifier: Programming Language :: Python :: 3.5
Classifier: Programming Language :: Python :: 3.6
Classifier: Programming Language :: Python :: 3.7
Classifier: Programming Language :: Python :: 3.8
Classifier: Programming Language :: Python :: 3.9
Classifier: Programming Language :: Python :: 3.10
Classifier: Programming Language :: Python :: 3.11
Classifier: Topic :: Software Development :: Libraries :: Python Modules
Classifier: Topic :: System :: Systems Administration
Classifier: Topic :: Security
Requires-Python: <4.0,>=3.10
License-File: LICENSE.txt
Requires-Dist: requests>=2.20.0
Requires-Dist: toml>=0.10.0
Requires-Dist: PyNaCl>=1.4.0
Requires-Dist: cyclonedx-bom>=3.0.0
Requires-Dist: pip-audit>=2.6.0
Requires-Dist: ko-poetry-audit-plugin==0.7.0
Provides-Extra: dev
Requires-Dist: pytest>=3.6.0; extra == "dev"
Requires-Dist: pytest-cov>=2.6.0; extra == "dev"
Requires-Dist: flake8>=3.5.0; extra == "dev"
Requires-Dist: ruff>=0.13.2; extra == "dev"
Requires-Dist: black>=18.9b0; python_version >= "3.6" and extra == "dev"
Requires-Dist: mypy>=0.650; python_version >= "3.5" and extra == "dev"
Dynamic: license-file
